pyminiping/__init__.py
pyminiping/cli.py
pyminiping/core.py
pyminiping/exceptions.py
pyminiping-1.0.2.dist-info/licenses/LICENSE
pyminiping-1.0.2.dist-info/METADATA
pyminiping-1.0.2.dist-info/WHEEL
pyminiping-1.0.2.dist-info/entry_points.txt
pyminiping-1.0.2.dist-info/top_level.txt
pyminiping-1.0.2.dist-info/RECORD
