Metadata-Version: 2.4
Name: pyminiping
Version: 1.0.2
Summary: Pure Python ICMP ping with statistics and hop count
Home-page: https://github.com/roxy-wi/pyminiping
Author: Pavel Loginov
Author-email: aidaho@roxy-wi.org
License: MIT
Classifier: Programming Language :: Python :: 3
Classifier: Operating System :: POSIX :: Linux
Classifier: Intended Audience :: Developers
Classifier: License :: OSI Approved :: MIT License
Classifier: Topic :: System :: Networking :: Monitoring
Requires-Python: >=3.7
License-File: LICENSE
Dynamic: author
Dynamic: author-email
Dynamic: classifier
Dynamic: description
Dynamic: description-content-type
Dynamic: home-page
Dynamic: license
Dynamic: license-file
Dynamic: requires-python
Dynamic: summary
